pyexcel/__init__.py
pyexcel/__version__.py
pyexcel/_compact.py
pyexcel/book.py
pyexcel/constants.py
pyexcel/cookbook.py
pyexcel/core.py
pyexcel/deprecated.py
pyexcel/exceptions.py
pyexcel/parser.py
pyexcel/renderer.py
pyexcel/sheet.py
pyexcel/source.py
pyexcel/docstrings/__init__.py
pyexcel/docstrings/core.py
pyexcel/docstrings/garbagecollector.py
pyexcel/docstrings/keywords.py
pyexcel/docstrings/meta.py
pyexcel/internal/__init__.py
pyexcel/internal/attributes.py
pyexcel/internal/common.py
pyexcel/internal/core.py
pyexcel/internal/garbagecollector.py
pyexcel/internal/generators.py
pyexcel/internal/meta.py
pyexcel/internal/plugins.py
pyexcel/internal/source_plugin.py
pyexcel/internal/utils.py
pyexcel/internal/sheets/__init__.py
pyexcel/internal/sheets/_shared.py
pyexcel/internal/sheets/column.py
pyexcel/internal/sheets/extended_list.py
pyexcel/internal/sheets/formatters.py
pyexcel/internal/sheets/matrix.py
pyexcel/internal/sheets/row.py
pyexcel/plugins/__init__.py
pyexcel/plugins/parsers/__init__.py
pyexcel/plugins/parsers/django.py
pyexcel/plugins/parsers/excel.py
pyexcel/plugins/parsers/sqlalchemy.py
pyexcel/plugins/renderers/__init__.py
pyexcel/plugins/renderers/_texttable.py
pyexcel/plugins/renderers/django.py
pyexcel/plugins/renderers/excel.py
pyexcel/plugins/renderers/sqlalchemy.py
pyexcel/plugins/sources/__init__.py
pyexcel/plugins/sources/db_sources.py
pyexcel/plugins/sources/django.py
pyexcel/plugins/sources/file_input.py
pyexcel/plugins/sources/file_output.py
pyexcel/plugins/sources/http.py
pyexcel/plugins/sources/memory_input.py
pyexcel/plugins/sources/output_to_memory.py
pyexcel/plugins/sources/params.py
pyexcel/plugins/sources/querysets.py
pyexcel/plugins/sources/sheet_stream_source.py
pyexcel/plugins/sources/sqlalchemy.py
pyexcel/plugins/sources/pydata/__init__.py
pyexcel/plugins/sources/pydata/arraysource.py
pyexcel/plugins/sources/pydata/bookdict.py
pyexcel/plugins/sources/pydata/common.py
pyexcel/plugins/sources/pydata/dictsource.py
pyexcel-0.7.1.dist-info/LICENSE
pyexcel-0.7.1.dist-info/METADATA
pyexcel-0.7.1.dist-info/WHEEL
pyexcel-0.7.1.dist-info/top_level.txt
pyexcel-0.7.1.dist-info/RECORD
