Metadata-Version: 2.1
Name: pyexcel
Version: 0.7.1
Summary: A wrapper library that provides one API to read, manipulate and writedata in different excel formats
Home-page: https://github.com/pyexcel/pyexcel
Download-URL: https://github.com/pyexcel/pyexcel/archive/0.7.1.tar.gz
Author: C.W.
Author-email: info@pyexcel.org
License: New BSD
Keywords: python,tsv,tsvzcsv,csvz,xls,xlsx,ods
Classifier: Topic :: Software Development :: Libraries
Classifier: Programming Language :: Python
Classifier: Intended Audience :: Developers
Classifier: Programming Language :: Python :: 3 :: Only
Classifier: Programming Language :: Python :: 3.6
Classifier: Programming Language :: Python :: 3.7
Classifier: Programming Language :: Python :: 3.8
Classifier: Development Status :: 3 - Alpha
Requires-Python: >=3.6
License-File: LICENSE
Requires-Dist: lml>=0.0.4
Requires-Dist: pyexcel-io>=0.6.2
Requires-Dist: texttable>=0.8.2
Provides-Extra: xls
Requires-Dist: pyexcel-xls>=0.6.0; extra == "xls"
Provides-Extra: xlsx
Requires-Dist: pyexcel-xlsx>=0.6.0; extra == "xlsx"
Provides-Extra: ods
Requires-Dist: pyexcel-ods3>=0.6.0; extra == "ods"
